realtimex_cli_mcps/__init__.py
realtimex_cli_mcps/cli.py
realtimex_cli_mcps/data/ansiweather/1.19.0/DOC_STR.txt
realtimex_cli_mcps/data/ansiweather/1.19.0/FUNC_SPEC.json
realtimex_cli_mcps/data/ansiweather/latest/DOC_STR.txt
realtimex_cli_mcps/data/ansiweather/latest/FUNC_SPEC.json
realtimex_cli_mcps/setup.py
realtimex_cli_mcps/tools/ansiweather/setup.py
realtimex_cli_mcps/tools/doctranslate_translate/output.py
realtimex_cli_mcps/tools/doctranslate_translate/setup.py
realtimex_cli_mcps/utils.py
realtimex_cli_mcps-1.0.8.dist-info/WHEEL
realtimex_cli_mcps-1.0.8.dist-info/entry_points.txt
realtimex_cli_mcps-1.0.8.dist-info/METADATA
realtimex_cli_mcps-1.0.8.dist-info/RECORD
