Metadata-Version: 2.3
Name: realtimex-cli-mcps
Version: 1.0.8
Summary: Add your description here
Author: rta_phuongnguyen
Author-email: rta_phuongnguyen <phuongnguyen@rtanalytics.vn>
Requires-Dist: fastmcp
Requires-Dist: openai
Requires-Python: >=3.11
